{
  "recipe_list": [
    {
      "name": "Aus nix irgend was",
      "fav": true,
      "ingredients": [
        ["Paprika", " ", " "],
        ["Nudel", " ", " "],
        ["Würstchen", " ", " "],
        ["Eier", " ", " "]
      ],
      "preparation": ""
    },
    {
      "name": "Bratwurst",
      "fav": true,
      "ingredients": [
        ["Bratwurst", " ", " "],
        ["Kartoffeln", " ", " "]
      ],
      "preparation": ""
    },
    {
      "name": "Chili con carne",
      "fav": true,
      "ingredients": [
        ["Hackfleisch", " ", " "],
        ["Bonen", " ", " "],
        ["Mais", " ", " "],
        ["gehackte Tomaten", " ", " "]
      ],
      "preparation": ""
    },
    {
      "name": "Frikadellen",
      "fav": false,
      "ingredients": [
        ["Hackfleisch", " ", " "],
        ["Brötchen", " ", " "],
        ["Eier", " ", " "],
        ["Gewürze", " ", " "]
      ],
      "preparation": ""
    },
    {
      "name": "Kartoffel-Auflauf",
      "fav": false,
      "ingredients": [],
      "preparation": ""
    },
    {
      "name": "Kartoffelecken",
      "fav": false,
      "ingredients": [
        ["Kartoffeln", " ", " "],
        ["Zwiebeln", " ", " "]
      ],
      "preparation": "",
      "test": true
    },
    {
      "name": "Kürbiscreme-Suppe",
      "fav": false,
      "ingredients": [],
      "preparation": ""
    },
    {
      "name": "Lachs a la Provence",
      "fav": false,
      "ingredients": [
        ["Lachs", " ", " "],
        ["Bacon", " ", " "],
        ["Tomaten", " ", " "],
        ["Reis", " ", " "]
      ],
      "preparation": ""
    },
    {
      "name": "Lasagne",
      "fav": true,
      "ingredients": [
        ["Rinderhack", " ", " "],
        ["Lasagne Blätter", " ", " "],
        ["Creme Fraiche", " ", " "],
        ["Zwiebeln", " ", " "]
      ],
      "preparation": ""
    },
    {
      "name": "Maultaschen-Suppe",
      "fav": true,
      "ingredients": [
        ["Maultaschen", " ", " "],
        ["Lauch", " ", " "],
        ["Würstchen", " ", " "],
        ["Brokkoli", " ", " "],
        ["Karotten", " ", " "],
        ["Chilli", " ", " "],
        ["Ingwer", " ", " "],
        ["Zwiebel", "1000", "Stk."]
      ],
      "preparation": "",
      "test": true
    },
    {
      "name": "Pizza",
      "fav": true,
      "ingredients": [
        ["Teig", 1, "Stk."],
        ["Soße", 1, "Stk."],
        ["Salami", "1", "Stk."],
        ["Paprika", 1, "Stk."],
        ["Zwiebel", "", "g"]
      ],
      "preparation": "Zubereitung",
      "test": true
    },
    {
      "name": "Reis-Gemüse",
      "fav": false,
      "ingredients": [
        ["Reis", " ", " "],
        ["Gemüse", " ", " "]
      ],
      "preparation": ""
    },
    {
      "name": "Reis-Spezial",
      "fav": false,
      "ingredients": [],
      "preparation": ""
    },
    {
      "name": "Rindergulasch",
      "fav": true,
      "ingredients": [
        ["Rindfleisch", " ", " "],
        ["Zwiebeln", " ", " "],
        ["Rinderbrühe", " ", " "],
        ["Gewürze", " ", " "]
      ],
      "preparation": ""
    },
    {
      "name": "Spaghetti",
      "fav": false,
      "ingredients": [
        ["Nudel", 300, "g"],
        ["Tomatensoße", 1, "Stk."],
        ["Passierte Tomaten", 1, "Stk."],
        ["Zwiebel", "1", "g"]
      ],
      "preparation": "Zubereitung",
      "test": true
    },
    {
      "name": "ToGeNu-Pfanne",
      "fav": false,
      "ingredients": [
        ["Nudel", " ", " "],
        ["Zucchini", " ", " "],
        ["Kohlrabi", " ", " "],
        ["Zwiebel", "", "g"]
      ],
      "preparation": "",
      "test": true
    },
    {
      "name": "Tortellini",
      "fav": true,
      "ingredients": [
        ["Tortellini", " ", " "],
        ["Milch", " ", " "],
        ["Sahne", " ", " "]
      ],
      "preparation": ""
    },
    {
      "name": "Wirsing-Gemüse",
      "fav": false,
      "ingredients": [
        ["Wirsing", " ", " "],
        ["Zwiebeln", " ", " "],
        ["Milch", " ", " "],
        ["Muskat", " ", " "]
      ],
      "preparation": ""
    }
  ],
  "shopping_list": {},
  "weekly_plan": {}
}
